k8s_itests/__init__.py
k8s_itests/test_autoscaling.py
k8s_itests/utils.py
paasta_tools/__init__.py
paasta_tools/adhoc_tools.py
paasta_tools/apply_external_resources.py
paasta_tools/async_utils.py
paasta_tools/bounce_lib.py
paasta_tools/broadcast_log_to_services.py
paasta_tools/cassandracluster_tools.py
paasta_tools/check_autoscaler_max_instances.py
paasta_tools/check_cassandracluster_services_replication.py
paasta_tools/check_flink_services_health.py
paasta_tools/check_kubernetes_api.py
paasta_tools/check_kubernetes_services_replication.py
paasta_tools/check_oom_events.py
paasta_tools/check_services_replication_tools.py
paasta_tools/check_spark_jobs.py
paasta_tools/cleanup_expired_autoscaling_overrides.py
paasta_tools/cleanup_kubernetes_cr.py
paasta_tools/cleanup_kubernetes_crd.py
paasta_tools/cleanup_kubernetes_jobs.py
paasta_tools/cleanup_tron_namespaces.py
paasta_tools/clusterman.py
paasta_tools/config_utils.py
paasta_tools/delete_kubernetes_deployments.py
paasta_tools/deployment_utils.py
paasta_tools/docker_wrapper.py
paasta_tools/docker_wrapper_imports.py
paasta_tools/drain_lib.py
paasta_tools/dump_locally_running_services.py
paasta_tools/eks_tools.py
paasta_tools/envoy_tools.py
paasta_tools/firewall.py
paasta_tools/firewall_logging.py
paasta_tools/firewall_update.py
paasta_tools/flink_tools.py
paasta_tools/flinkeks_tools.py
paasta_tools/generate_all_deployments
paasta_tools/generate_authenticating_services.py
paasta_tools/generate_deployments_for_service.py
paasta_tools/generate_services_file.py
paasta_tools/generate_services_yaml.py
paasta_tools/hacheck.py
paasta_tools/iptables.py
paasta_tools/kafkacluster_tools.py
paasta_tools/kubernetes_tools.py
paasta_tools/list_kubernetes_service_instances.py
paasta_tools/list_tron_namespaces.py
paasta_tools/long_running_service_tools.py
paasta_tools/mac_address.py
paasta_tools/marathon_dashboard.py
paasta_tools/mesos_tools.py
paasta_tools/monitoring_tools.py
paasta_tools/monkrelaycluster_tools.py
paasta_tools-1.36.3.dist-info/licenses/LICENSE
paasta_tools-1.36.3.dist-info/METADATA
paasta_tools-1.36.3.dist-info/WHEEL
paasta_tools-1.36.3.dist-info/entry_points.txt
paasta_tools-1.36.3.dist-info/top_level.txt
paasta_tools-1.36.3.dist-info/RECORD
