Metadata-Version: 2.4
Name: paasta-tools
Version: 1.36.3
Summary: Tools for Yelps SOA infrastructure
Author: Compute Infrastructure @ Yelp
Author-email: compute-infra@yelp.com
Provides: paasta_tools
Requires-Python: >=3.9.0
License-File: LICENSE
Requires-Dist: a-sync>=0.5.0
Requires-Dist: aiohttp>=3.5.4
Requires-Dist: argcomplete>=0.8.1
Requires-Dist: boto
Requires-Dist: boto3
Requires-Dist: boto3-type-annotations
Requires-Dist: botocore
Requires-Dist: bravado>=10.2.0
Requires-Dist: certifi
Requires-Dist: choice>=0.1
Requires-Dist: containerd
Requires-Dist: cookiecutter>=1.4.0
Requires-Dist: croniter
Requires-Dist: docker
Requires-Dist: dulwich>=0.17.3
Requires-Dist: environment-tools
Requires-Dist: ephemeral-port-reserve>=1.0.1
Requires-Dist: graphviz
Requires-Dist: grpcio
Requires-Dist: gunicorn
Requires-Dist: humanfriendly
Requires-Dist: humanize>=0.5.1
Requires-Dist: inotify>=0.2.8
Requires-Dist: ipaddress>=1.0.22
Requires-Dist: isodate>=0.7.2
Requires-Dist: jsonschema[format]
Requires-Dist: kazoo>=2.0.0
Requires-Dist: kubernetes<35.0.0,>=29.0.0
Requires-Dist: ldap3
Requires-Dist: manhole
Requires-Dist: mypy-extensions>=0.3.0
Requires-Dist: nats-py
Requires-Dist: nulltype
Requires-Dist: objgraph
Requires-Dist: ply
Requires-Dist: progressbar2>=4.3.2
Requires-Dist: prometheus-client
Requires-Dist: pymesos>=0.2.0
Requires-Dist: pyramid-swagger>=2.3.0
Requires-Dist: pyramid>=2.0.2
Requires-Dist: pysensu-yelp>=0.3.4
Requires-Dist: PyStaticConfiguration
Requires-Dist: python-crontab>=2.1.1
Requires-Dist: python-dateutil>=2.4.0
Requires-Dist: python-iptables
Requires-Dist: pytimeparse>=1.1.0
Requires-Dist: pytz>=2014.10
Requires-Dist: requests>=2.18.4
Requires-Dist: requests-cache>=0.4.10
Requires-Dist: retry
Requires-Dist: ruamel.yaml
Requires-Dist: sensu-plugin
Requires-Dist: service-configuration-lib>=3.3.5
Requires-Dist: signalfx
Requires-Dist: slackclient>=1.2.1
Requires-Dist: sticht>=1.1.0
Requires-Dist: syslogmp
Requires-Dist: transitions
Requires-Dist: typing-extensions
Requires-Dist: tzlocal
Requires-Dist: urllib3
Requires-Dist: utaw>=0.2.0
Requires-Dist: wsgicors
Dynamic: author
Dynamic: author-email
Dynamic: license-file
Dynamic: provides
Dynamic: requires-dist
Dynamic: requires-python
Dynamic: summary
